cosmopyro/__init__.py
cosmopyro/utils/class_utils.py
cosmopyro-0.0.1a1.dist-info/licenses/LICENSE
cosmopyro-0.0.1a1.dist-info/METADATA
cosmopyro-0.0.1a1.dist-info/WHEEL
cosmopyro-0.0.1a1.dist-info/top_level.txt
cosmopyro-0.0.1a1.dist-info/RECORD
