Metadata-Version: 2.4
Name: cosmopyro
Version: 0.0.1a1
Summary: Population Inference with gravitational-wave dark-siren
Author-email: Konstantin Leyde <konstantin.leyde@gmail.com>
License-Expression: MIT
Project-URL: Homepage, https://github.com/konstantinleyde/cosmopyro
Project-URL: Issues, https://github.com/konstantinleyde/cosmopyro/issues
Keywords: hamiltonian monte-carlo,cosmology,gravitational waves
Classifier: Programming Language :: Python :: 3
Classifier: Operating System :: OS Independent
Requires-Python: >=3.11
License-File: LICENSE
Requires-Dist: jax
Requires-Dist: numpyro
Requires-Dist: matplotlib
Requires-Dist: numpy
Requires-Dist: pandas
Requires-Dist: scipy
Requires-Dist: corner
Requires-Dist: pyyaml
Requires-Dist: arviz
Requires-Dist: optax
Requires-Dist: rich
Requires-Dist: healpy
Dynamic: license-file
